statuspageio/__init__.py
statuspageio/client.py
statuspageio/configuration.py
statuspageio/errors.py
statuspageio/http_client.py
statuspageio/services.py
statuspageio/version.py
xandr_statuspageio-0.0.8.dist-info/METADATA
xandr_statuspageio-0.0.8.dist-info/WHEEL
xandr_statuspageio-0.0.8.dist-info/top_level.txt
xandr_statuspageio-0.0.8.dist-info/RECORD
